bitnodes_hardware-0.1.0.dist-info/WHEEL
bitnodes_hardware-0.1.0.dist-info/METADATA
bitnodes_hardware-0.1.0.dist-info/DESCRIPTION.rst
bitnodes_hardware-0.1.0.dist-info/RECORD
bitnodes_hardware-0.1.0.dist-info/metadata.json
bitnodes_hardware-0.1.0.dist-info/top_level.txt
hardware/settings.py
hardware/middleware.py
hardware/wsgi.py
hardware/__init__.py
hardware/urls.py
hardware/utils.py
hardware/rpc.py
hardware/celery.py
hardware/administration/__init__.py
hardware/administration/urls.py
hardware/administration/models.py
hardware/administration/forms.py
hardware/administration/tasks.py
hardware/administration/views.py
hardware/administration/tests/__init__.py
hardware/administration/tests/test_tasks.py
hardware/administration/tests/test_bitcoin_address.py
hardware/administration/management/__init__.py
hardware/administration/management/commands/__init__.py
hardware/administration/management/commands/create_bitcoin_conf.py
hardware/administration/migrations/__init__.py
hardware/administration/migrations/0001_initial.py
hardware/dashboard/__init__.py
hardware/dashboard/views.py
hardware/dashboard/templatetags/dashboard_tags.py
hardware/dashboard/templatetags/__init__.py
hardware/api/__init__.py
hardware/api/urls.py
hardware/api/tasks.py
hardware/api/views.py
hardware/api/tests/__init__.py
hardware/api/tests/test_tasks.py
