Metadata-Version: 2.0
Name: bitnodes-hardware
Version: 0.1.0
Summary: Django project for Bitnodes Hardware, a low footprint quad-core single-board computer built and configured to operate as a dedicated Bitcoin full node.
Home-page: https://github.com/ayeowch/bitnodes-hardware
Author: Addy Yeow Chin Heng
Author-email: ayeowch@gmail.com
License: MIT
Keywords: bitcoin network,full node,bitnodes hardware
Platform: UNKNOWN
Classifier: Development Status :: 4 - Beta
Classifier: Environment :: Web Environment
Classifier: Framework :: Django
Classifier: Intended Audience :: Developers
Classifier: Intended Audience :: End Users/Desktop
Classifier: License :: OSI Approved :: MIT License
Classifier: Operating System :: MacOS :: MacOS X
Classifier: Operating System :: POSIX :: Linux
Classifier: Programming Language :: Python
Classifier: Programming Language :: Python :: 2.7
Classifier: Topic :: Internet :: WWW/HTTP
Classifier: Topic :: System :: Hardware
Classifier: Topic :: System :: Monitoring
Classifier: Topic :: System :: Networking :: Monitoring
Classifier: Topic :: System :: Systems Administration
Requires-Dist: Django (>=1.8)
Requires-Dist: django-celery
Requires-Dist: django-debug-toolbar
Requires-Dist: django-supervisor
Requires-Dist: djangorestframework
Requires-Dist: gunicorn
Requires-Dist: psycopg2
Requires-Dist: redis
Requires-Dist: requests
Requires-Dist: tornado
